fastapi_autoroutes/__init__.py
fastapi_autoroutes/router.py
fastapi_autoroutes-0.1.2.dist-info/METADATA
fastapi_autoroutes-0.1.2.dist-info/WHEEL
fastapi_autoroutes-0.1.2.dist-info/top_level.txt
fastapi_autoroutes-0.1.2.dist-info/RECORD
