Metadata-Version: 2.4
Name: fastapi-autoroutes
Version: 0.1.2
Summary: Add your description here
Requires-Python: >=3.12
Requires-Dist: diskcache>=5.6.3
Requires-Dist: fastapi>=0.118.0
Requires-Dist: sqlmodel>=0.0.25
